LICENSE.txt
MANIFEST.in
README.txt
samica.py
setup.py
samicalib/__init__.py
samicalib.egg-info/PKG-INFO
samicalib.egg-info/SOURCES.txt
samicalib.egg-info/dependency_links.txt
samicalib.egg-info/top_level.txt
venv/bin/rst2html.py
venv/bin/rst2html4.py
venv/bin/rst2html5.py
venv/bin/rst2latex.py
venv/bin/rst2man.py
venv/bin/rst2odt.py
venv/bin/rst2odt_prepstyles.py
venv/bin/rst2pseudoxml.py
venv/bin/rst2s5.py
venv/bin/rst2xetex.py
venv/bin/rst2xml.py
venv/bin/rstpep2html.py
venv/lib/python3.10/site-packages/six.py
venv/lib/python3.10/site-packages/zipp.py
venv/lib/python3.10/site-packages/_distutils_hack/__init__.py
venv/lib/python3.10/site-packages/_distutils_hack/override.py
venv/lib/python3.10/site-packages/bleach/__init__.py
venv/lib/python3.10/site-packages/bleach/callbacks.py
venv/lib/python3.10/site-packages/bleach/css_sanitizer.py
venv/lib/python3.10/site-packages/bleach/html5lib_shim.py
venv/lib/python3.10/site-packages/bleach/linkifier.py
venv/lib/python3.10/site-packages/bleach/sanitizer.py
venv/lib/python3.10/site-packages/bleach/_vendor/__init__.py
venv/lib/python3.10/site-packages/bleach/_vendor/parse.py
venv/lib/python3.10/site-packages/bleach/_vendor/html5lib/__init__.py
venv/lib/python3.10/site-packages/bleach/_vendor/html5lib/_ihatexml.py
venv/lib/python3.10/site-packages/bleach/_vendor/html5lib/_inputstream.py
venv/lib/python3.10/site-packages/bleach/_vendor/html5lib/_tokenizer.py
venv/lib/python3.10/site-packages/bleach/_vendor/html5lib/_utils.py
venv/lib/python3.10/site-packages/bleach/_vendor/html5lib/constants.py
venv/lib/python3.10/site-packages/bleach/_vendor/html5lib/html5parser.py
venv/lib/python3.10/site-packages/bleach/_vendor/html5lib/serializer.py
venv/lib/python3.10/site-packages/bleach/_vendor/html5lib/_trie/__init__.py
venv/lib/python3.10/site-packages/bleach/_vendor/html5lib/_trie/_base.py
venv/lib/python3.10/site-packages/bleach/_vendor/html5lib/_trie/py.py
venv/lib/python3.10/site-packages/bleach/_vendor/html5lib/filters/__init__.py
venv/lib/python3.10/site-packages/bleach/_vendor/html5lib/filters/alphabeticalattributes.py
